gdelt/__init__.py
gdelt/base.py
gdelt/dateFuncs.py
gdelt/extractors.py
gdelt/getHeaders.py
gdelt/helpers.py
gdelt/inputChecks.py
gdelt/multipdf.py
gdelt/parallel.py
gdelt/vectorizingFuncs.py
gdelt-0.1.14.data/data/data/cameoCodes.json
gdelt-0.1.14.data/data/data/events1.csv
gdelt-0.1.14.data/data/data/events1samp.gz
gdelt-0.1.14.data/data/data/events2.csv
gdelt-0.1.14.data/data/data/events2Transsamp.gz
gdelt-0.1.14.data/data/data/events2listsamp.gz
gdelt-0.1.14.data/data/data/events2samp.gz
gdelt-0.1.14.data/data/data/events2samps.csv.zip
gdelt-0.1.14.data/data/data/gkg1.csv
gdelt-0.1.14.data/data/data/gkg1samp.gz
gdelt-0.1.14.data/data/data/gkg2.csv
gdelt-0.1.14.data/data/data/gkg2Transsamp.gz
gdelt-0.1.14.data/data/data/gkg2listsamp.gz
gdelt-0.1.14.data/data/data/gkg2samp.gz
gdelt-0.1.14.data/data/data/iatv.csv
gdelt-0.1.14.data/data/data/mentions.csv
gdelt-0.1.14.data/data/data/mentionsTranssamp.gz
gdelt-0.1.14.data/data/data/mentionslistsamp.gz
gdelt-0.1.14.data/data/data/mentionssamp.csv
gdelt-0.1.14.data/data/data/mentionssamp.gz
gdelt-0.1.14.data/data/data/visualgkg.csv
gdelt-0.1.14.dist-info/AUTHORS.rst
gdelt-0.1.14.dist-info/LICENSE
gdelt-0.1.14.dist-info/METADATA
gdelt-0.1.14.dist-info/WHEEL
gdelt-0.1.14.dist-info/top_level.txt
gdelt-0.1.14.dist-info/RECORD
