Metadata-Version: 2.1
Name: gdelt
Version: 0.1.14
Summary: Python-based framework to access and analyze Global Database of Events, Language, and Tone (GDELT) 1.0 or 2.0 data in a Python Pandas or R dataframe
Home-page: https://linwoodc3.github.io/gdeltPyR/
Author: Linwood Creekmore III
Author-email: valinvescap@gmail.com
Maintainer: Linwood Creekmore III
Maintainer-email: valinvescap@gmail.com
License:                     GNU GENERAL PUBLIC LICENSE
Project-URL: Homepage, https://linwoodc3.github.io/gdeltPyR/
Project-URL: Bug Tracker, https://github.com/linwoodc3/gdeltPyR/issues
Keywords: gdelt,pandas,tidy,data,api,python,news,geolocated
Platform: Any
Classifier: Development Status :: 3 - Alpha
Classifier: Intended Audience :: Science/Research
Classifier: Operating System :: OS Independent
Classifier: Topic :: Software Development :: Libraries :: Python Modules
Classifier: Topic :: Communications :: Chat
Classifier: Topic :: Internet
Classifier: Topic :: Scientific/Engineering :: Information Analysis
Classifier: Topic :: Internet :: WWW/HTTP :: Dynamic Content
Classifier: Programming Language :: Python
Classifier: Programming Language :: Python :: 3
Classifier: Programming Language :: Python :: 3.4
Classifier: Programming Language :: Python :: 3.5
Classifier: Programming Language :: Python :: 3.6
Requires-Python: >=3.7
License-File: LICENSE
License-File: AUTHORS.rst
Requires-Dist: numpy>=1.11.1
Requires-Dist: pandas>=0.23
Requires-Dist: requests>=2.31.0
Requires-Dist: python-dateutil>=2.8.2
Provides-Extra: geospatial
Requires-Dist: fiona>=1.6; extra == "geospatial"
Requires-Dist: shapely>=1.5; extra == "geospatial"
Requires-Dist: geopandas>1.7; extra == "geospatial"
Requires-Dist: mock; python_version < "3.3"
Requires-Dist: futures; python_version < "3.3"
Provides-Extra: r
Requires-Dist: pyarrow; extra == "r"
